django_dkim/__init__.py
django_dkim/backends/__init__.py
django_dkim/backends/console.py
django_dkim/backends/smtp.py
django_dkim/tests/__init__.py
django_dkim/tests/settings.py
django_dkim/tests/test_backends.py
django_dkim-0.1.3.dist-info/LICENSE
django_dkim-0.1.3.dist-info/METADATA
django_dkim-0.1.3.dist-info/WHEEL
django_dkim-0.1.3.dist-info/top_level.txt
django_dkim-0.1.3.dist-info/RECORD
