Metadata-Version: 2.1
Name: django-dkim
Version: 0.1.3
Summary: DKIM signing e-mail backend for Django
Home-page: https://gitlab.com/stinovlas/django-dkim
Author: Jan Musílek
Author-email: stinovlas@gmail.com
License: UNKNOWN
Platform: UNKNOWN
Classifier: Development Status :: 4 - Beta
Classifier: Environment :: Web Environment
Classifier: Framework :: Django
Classifier: Framework :: Django :: 2.2
Classifier: Framework :: Django :: 3.0
Classifier: Framework :: Django :: 3.1
Classifier: Framework :: Django :: 3.2
Classifier: Framework :: Django :: 4.0
Classifier: Intended Audience :: Developers
Classifier: License :: OSI Approved :: GNU General Public License v3 (GPLv3)
Classifier: Operating System :: OS Independent
Classifier: Programming Language :: Python
Classifier: Programming Language :: Python :: 3.5
Classifier: Programming Language :: Python :: 3.6
Classifier: Programming Language :: Python :: 3.7
Classifier: Programming Language :: Python :: 3.8
Classifier: Programming Language :: Python :: 3.9
Classifier: Programming Language :: Python :: 3.10
Classifier: Topic :: Internet :: WWW/HTTP
Classifier: Topic :: Internet :: WWW/HTTP :: Dynamic Content
Requires-Python: >=2.7, !=3.0.*, !=3.1.*, !=3.2.*, !=3.3.*, <4
License-File: LICENSE
Requires-Dist: Django (>=1.11)
Requires-Dist: dkimpy
Requires-Dist: future
Provides-Extra: quality
Requires-Dist: flake8 ; extra == 'quality'
Requires-Dist: isort ; extra == 'quality'
Requires-Dist: pydocstyle ; extra == 'quality'
Provides-Extra: test
Requires-Dist: mock ; extra == 'test'
